BomberNight/__init__.py
BomberNight/__main__.py
BomberNight/bomb.py
BomberNight/game.py
BomberNight/main.py
BomberNight/menu.py
BomberNight/player.py
BomberNight/utils.py
BomberNight/images/bomba.png
BomberNight/images/inicio.png
BomberNight/images/mapa.jpg
BomberNight/images/menu.jpg
BomberNight/images/player.png
BomberNight-0.0.4.post0.dist-info/LICENSE
BomberNight-0.0.4.post0.dist-info/METADATA
BomberNight-0.0.4.post0.dist-info/WHEEL
BomberNight-0.0.4.post0.dist-info/entry_points.txt
BomberNight-0.0.4.post0.dist-info/top_level.txt
BomberNight-0.0.4.post0.dist-info/RECORD
