Metadata-Version: 2.1
Name: BomberNight
Version: 0.0.4.post0
Summary: Releitura do Bomberman
Home-page: https://github.com/juliohsu/BomberNight
Author: Júlio Hsu
Author-email: tst700900@gmail.com
License: MIT
Keywords: jogo,game,bomberman,arcade,ação
Platform: UNKNOWN
Requires-Python: >=3.6
Requires-Dist: pygame (>=2.0)
